MANIFEST.in
README
setup.py
JitViewer.egg-info/PKG-INFO
JitViewer.egg-info/SOURCES.txt
JitViewer.egg-info/dependency_links.txt
JitViewer.egg-info/not-zip-safe
JitViewer.egg-info/requires.txt
JitViewer.egg-info/top_level.txt
_jitviewer/__init__.py
_jitviewer/app.py
_jitviewer/display.py
_jitviewer/misc.py
_jitviewer/parser.py
_jitviewer/static/DroidSansMono.ttf
_jitviewer/static/app.js
_jitviewer/static/favicon.ico
_jitviewer/static/jquery-1.2.6.min.js
_jitviewer/static/jquery.min.js
_jitviewer/static/jquery.scrollTo-1.4.1.js
_jitviewer/static/jquery.scrollTo-1.4.2-min.js
_jitviewer/static/loop.js
_jitviewer/static/pygments.css
_jitviewer/static/qt_workaround.css
_jitviewer/static/script.js
_jitviewer/static/style.css
_jitviewer/static/canjs/1.1.4/can.construct.proxy.js
_jitviewer/static/canjs/1.1.4/can.construct.super.js
_jitviewer/static/canjs/1.1.4/can.control.plugin.js
_jitviewer/static/canjs/1.1.4/can.dojo.js
_jitviewer/static/canjs/1.1.4/can.dojo.min.js
_jitviewer/static/canjs/1.1.4/can.fixture.js
_jitviewer/static/canjs/1.1.4/can.jquery-all.js
_jitviewer/static/canjs/1.1.4/can.jquery-all.min.js
_jitviewer/static/canjs/1.1.4/can.jquery.js
_jitviewer/static/canjs/1.1.4/can.jquery.min.js
_jitviewer/static/canjs/1.1.4/can.mootools.js
_jitviewer/static/canjs/1.1.4/can.mootools.min.js
_jitviewer/static/canjs/1.1.4/can.observe.attributes.js
_jitviewer/static/canjs/1.1.4/can.observe.backup.js
_jitviewer/static/canjs/1.1.4/can.observe.delegate.js
_jitviewer/static/canjs/1.1.4/can.observe.setter.js
_jitviewer/static/canjs/1.1.4/can.observe.validations.js
_jitviewer/static/canjs/1.1.4/can.view.modifiers.js
_jitviewer/static/canjs/1.1.4/can.view.mustache.js
_jitviewer/static/canjs/1.1.4/can.yui.js
_jitviewer/static/canjs/1.1.4/can.yui.min.js
_jitviewer/static/canjs/1.1.4/can.zepto.js
_jitviewer/static/canjs/1.1.4/can.zepto.min.js
_jitviewer/static/canjs/1.1.4/amd/can.js
_jitviewer/static/canjs/1.1.4/amd/can/construct.js
_jitviewer/static/canjs/1.1.4/amd/can/control.js
_jitviewer/static/canjs/1.1.4/amd/can/model.js
_jitviewer/static/canjs/1.1.4/amd/can/observe.js
_jitviewer/static/canjs/1.1.4/amd/can/route.js
_jitviewer/static/canjs/1.1.4/amd/can/view.js
